karrio/mappers/seko/__init__.py
karrio/mappers/seko/mapper.py
karrio/mappers/seko/proxy.py
karrio/mappers/seko/settings.py
karrio/plugins/seko/__init__.py
karrio/providers/seko/__init__.py
karrio/providers/seko/error.py
karrio/providers/seko/manifest.py
karrio/providers/seko/rate.py
karrio/providers/seko/tracking.py
karrio/providers/seko/units.py
karrio/providers/seko/utils.py
karrio/providers/seko/shipment/__init__.py
karrio/providers/seko/shipment/cancel.py
karrio/providers/seko/shipment/create.py
karrio/schemas/seko/__init__.py
karrio/schemas/seko/error_response.py
karrio/schemas/seko/manifest_response.py
karrio/schemas/seko/rating_request.py
karrio/schemas/seko/rating_response.py
karrio/schemas/seko/shipping_request.py
karrio/schemas/seko/shipping_response.py
karrio/schemas/seko/tracking_response.py
karrio_seko-2026.1.4.dist-info/METADATA
karrio_seko-2026.1.4.dist-info/WHEEL
karrio_seko-2026.1.4.dist-info/entry_points.txt
karrio_seko-2026.1.4.dist-info/top_level.txt
karrio_seko-2026.1.4.dist-info/RECORD
